{
  "type": "minecraft:crafting_shapeless",
  "ingredients": [
    {
      "item": "chicken_roost:chicken_essence_tier_6"
    },
    {
      "item": "chicken_roost:chicken_essence_tier_6"
    },
    {
      "item": "chicken_roost:chicken_essence_tier_6"
    },
    {
      "item": "chicken_roost:chicken_food_tier_5"
    },
    {
      "item": "chicken_roost:chicken_food_tier_5"
    },
    {
      "item": "chicken_roost:chicken_food_tier_5"
    },
    {
      "item": "chicken_roost:chicken_food_tier_5"
    },
    {
      "item": "chicken_roost:chicken_food_tier_5"
    },
    {
      "item": "chicken_roost:chicken_food_tier_5"
    }
  ],
  "result": {
    "id": "chicken_roost:chicken_food_tier_6",
    "count": 1
  }
}